{
    "data": [
        {
            "id": "595826137486081276",
            "store_name": "tuco-test-name",
            "tags": [
                "zzs-test8",
                "root的标签1"
            ],
            "store_status": "available",
            "sync_status": "success",
            "store_id": "422115",
            "account": "wuxueting+7@shoplazza.com",
            "skit_num": "746",
            "subscribe_num": "16",
            "sync_failure_reason": "",
            "template_type": "main_template",
            "created_at": "2025-12-31T04:00:21Z",
            "updated_at": "2026-01-21T16:46:57"
        },
        {
            "id": "555557316687037058",
            "store_name": "tuco-copy",
            "tags": [
                "zzs-test8"
            ],
            "store_status": "expired",
            "sync_status": "success",
            "store_id": "2265123",
            "account": "mengdajun@shoplazza.com",
            "skit_num": "285",
            "subscribe_num": "6",
            "sync_failure_reason": "",
            "template_type": "template",
            "created_at": "2025-09-11T01:06:26Z",
            "updated_at": "2026-01-21T12:00:27"
        },
        {
            "id": "552414383871889424",
            "store_name": "xishng-migrate-1706253997202401269",
            "tags": [],
            "store_status": "expired",
            "sync_status": "failure",
            "store_id": "1183408",
            "account": "zhaoxisheng@shoplazza.com",
            "skit_num": "0",
            "subscribe_num": "0",
            "sync_failure_reason": "not found Subscription collection",
            "template_type": "",
            "created_at": "2025-09-02T08:57:32Z",
            "updated_at": "2026-01-22T12:00:36"
        },
        {
            "id": "552414383095943184",
            "store_name": "xishng-migrate1702285842121211",
            "tags": [],
            "store_status": "expired",
            "sync_status": "failure",
            "store_id": "659331",
            "account": "zhaoxisheng@shoplazza.com",
            "skit_num": "0",
            "subscribe_num": "0",
            "sync_failure_reason": "not found Subscription collection",
            "template_type": "",
            "created_at": "2025-09-02T08:57:32Z",
            "updated_at": "2026-01-22T12:00:36"
        },
        {
            "id": "552414383477624848",
            "store_name": "xishng-migrate1704694594000202401",
            "tags": [],
            "store_status": "expired",
            "sync_status": "failure",
            "store_id": "851025",
            "account": "zhaoxisheng@shoplazza.com",
            "skit_num": "0",
            "subscribe_num": "0",
            "sync_failure_reason": "not found Subscription collection",
            "template_type": "",
            "created_at": "2025-09-02T08:57:32Z",
            "updated_at": "2026-01-22T12:00:36"
        },
        {
            "id": "552414383351795728",
            "store_name": "xishng-migrate1704686112202401",
            "tags": [],
            "store_status": "available",
            "sync_status": "failure",
            "store_id": "821048",
            "account": "zhaoxisheng@shoplazza.com",
            "skit_num": "0",
            "subscribe_num": "0",
            "sync_failure_reason": "not found Subscription collection",
            "template_type": "",
            "created_at": "2025-09-02T08:57:32Z",
            "updated_at": "2026-01-22T12:00:36"
        },
        {
            "id": "552414382760398864",
            "store_name": "xishng-migrate-test1701846375",
            "tags": [],
            "store_status": "expired",
            "sync_status": "failure",
            "store_id": "652577",
            "account": "zhaoxisheng@shoplazza.com",
            "skit_num": "0",
            "subscribe_num": "0",
            "sync_failure_reason": "not found Subscription collection",
            "template_type": "",
            "created_at": "2025-09-02T08:57:32Z",
            "updated_at": "2026-01-22T12:00:36"
        },
        {
            "id": "552414382814924816",
            "store_name": "xishng-migrate170191350912",
            "tags": [],
            "store_status": "expired",
            "sync_status": "failure",
            "store_id": "653512",
            "account": "zhaoxisheng@shoplazza.com",
            "skit_num": "0",
            "subscribe_num": "0",
            "sync_failure_reason": "not found Subscription collection",
            "template_type": "",
            "created_at": "2025-09-02T08:57:32Z",
            "updated_at": "2026-01-22T12:00:36"
        },
        {
            "id": "552414383234355216",
            "store_name": "xishng1703050582",
            "tags": [],
            "store_status": "expired",
            "sync_status": "failure",
            "store_id": "667788",
            "account": "zhaoxisheng@shoplazza.com",
            "skit_num": "0",
            "subscribe_num": "0",
            "sync_failure_reason": "not found Subscription collection",
            "template_type": "",
            "created_at": "2025-09-02T08:57:32Z",
            "updated_at": "2026-01-22T12:00:36"
        },
        {
            "id": "552414382827507728",
            "store_name": "xishng-migrate170196035812",
            "tags": [
                "root的标签1"
            ],
            "store_status": "expired",
            "sync_status": "failure",
            "store_id": "655889",
            "account": "zhaoxisheng@shoplazza.com",
            "skit_num": "0",
            "subscribe_num": "0",
            "sync_failure_reason": "not found Subscription collection",
            "template_type": "",
            "created_at": "2025-09-02T08:57:32Z",
            "updated_at": "2026-01-22T12:00:36"
        },
        {
            "id": "552414383657979920",
            "store_name": "xishng-migrate-1706240233",
            "tags": [],
            "store_status": "expired",
            "sync_status": "failure",
            "store_id": "1183315",
            "account": "zhaoxisheng@shoplazza.com",
            "skit_num": "0",
            "subscribe_num": "0",
            "sync_failure_reason": "not found Subscription collection",
            "template_type": "",
            "created_at": "2025-09-02T08:57:32Z",
            "updated_at": "2026-01-22T12:00:36"
        },
        {
            "id": "552414383771226128",
            "store_name": "cod-risk-control-xs",
            "tags": [],
            "store_status": "available",
            "sync_status": "failure",
            "store_id": "1243012",
            "account": "zhaoxisheng@shoplazza.com",
            "skit_num": "0",
            "subscribe_num": "0",
            "sync_failure_reason": "not found Subscription collection",
            "template_type": "",
            "created_at": "2025-09-02T08:57:32Z",
            "updated_at": "2026-01-22T12:00:36"
        },
        {
            "id": "552414383582482448",
            "store_name": "xishng1704694999",
            "tags": [],
            "store_status": "expired",
            "sync_status": "failure",
            "store_id": "881019",
            "account": "zhaoxisheng@shoplazza.com",
            "skit_num": "0",
            "subscribe_num": "0",
            "sync_failure_reason": "not found Subscription collection",
            "template_type": "",
            "created_at": "2025-09-02T08:57:32Z",
            "updated_at": "2026-01-22T12:00:36"
        },
        {
            "id": "552414383163052048",
            "store_name": "xishng1703045322",
            "tags": [],
            "store_status": "available",
            "sync_status": "failure",
            "store_id": "667787",
            "account": "zhaoxisheng@shoplazza.com",
            "skit_num": "0",
            "subscribe_num": "0",
            "sync_failure_reason": "not found Subscription collection",
            "template_type": "",
            "created_at": "2025-09-02T08:57:32Z",
            "updated_at": "2026-01-22T12:00:36"
        },
        {
            "id": "552414384123547664",
            "store_name": "shopift-next-mig20250224202502241",
            "tags": [],
            "store_status": "available",
            "sync_status": "failure",
            "store_id": "2211521",
            "account": "zhaoxisheng@shoplazza.com",
            "skit_num": "0",
            "subscribe_num": "0",
            "sync_failure_reason": "not found Subscription collection",
            "template_type": "",
            "created_at": "2025-09-02T08:57:33Z",
            "updated_at": "2026-01-22T12:00:36"
        },
        {
            "id": "552414384035467280",
            "store_name": "shopline-mig-17399536610219",
            "tags": [],
            "store_status": "available",
            "sync_status": "failure",
            "store_id": "2208917",
            "account": "zhaoxisheng@shoplazza.com",
            "skit_num": "0",
            "subscribe_num": "0",
            "sync_failure_reason": "not found Subscription collection",
            "template_type": "",
            "created_at": "2025-09-02T08:57:33Z",
            "updated_at": "2026-01-22T12:00:36"
        },
        {
            "id": "552414383943192592",
            "store_name": "migrate-1739239151202502112",
            "tags": [],
            "store_status": "available",
            "sync_status": "failure",
            "store_id": "2203641",
            "account": "zhaoxisheng@shoplazza.com",
            "skit_num": "0",
            "subscribe_num": "0",
            "sync_failure_reason": "not found Subscription collection",
            "template_type": "",
            "created_at": "2025-09-02T08:57:32Z",
            "updated_at": "2026-01-22T12:00:36"
        },
        {
            "id": "552414382978502672",
            "store_name": "xishng-migrate170205747912",
            "tags": [
                "root的标签1"
            ],
            "store_status": "expired",
            "sync_status": "failure",
            "store_id": "657668",
            "account": "zhaoxisheng@shoplazza.com",
            "skit_num": "0",
            "subscribe_num": "0",
            "sync_failure_reason": "not found Subscription collection",
            "template_type": "",
            "created_at": "2025-09-02T08:57:32Z",
            "updated_at": "2026-01-22T12:00:36"
        },
        {
            "id": "552414384136130576",
            "store_name": "xishng-mig-1741136679202503052",
            "tags": [],
            "store_status": "available",
            "sync_status": "failure",
            "store_id": "2216944",
            "account": "zhaoxisheng@shoplazza.com",
            "skit_num": "0",
            "subscribe_num": "0",
            "sync_failure_reason": "not found Subscription collection",
            "template_type": "",
            "created_at": "2025-09-02T08:57:33Z",
            "updated_at": "2026-01-22T12:00:36"
        },
        {
            "id": "552414383326629904",
            "store_name": "xishng17030604551220",
            "tags": [],
            "store_status": "expired",
            "sync_status": "failure",
            "store_id": "668022",
            "account": "zhaoxisheng@shoplazza.com",
            "skit_num": "0",
            "subscribe_num": "0",
            "sync_failure_reason": "not found Subscription collection",
            "template_type": "",
            "created_at": "2025-09-02T08:57:32Z",
            "updated_at": "2026-01-22T12:00:36"
        }
    ],
    "count": "179"
}